streamlit_qrcode_scanner/__init__.py
streamlit_qrcode_scanner/frontend/html5-qrcode.min.js
streamlit_qrcode_scanner/frontend/index.html
streamlit_qrcode_scanner/frontend/main.js
streamlit_qrcode_scanner/frontend/streamlit-component-lib.js
streamlit_qrcode_scanner-0.1.2.dist-info/LICENSE
streamlit_qrcode_scanner-0.1.2.dist-info/METADATA
streamlit_qrcode_scanner-0.1.2.dist-info/WHEEL
streamlit_qrcode_scanner-0.1.2.dist-info/top_level.txt
streamlit_qrcode_scanner-0.1.2.dist-info/RECORD
