Metadata-Version: 2.1
Name: streamlit-qrcode-scanner
Version: 0.1.2
Summary: QRCode scanner use html5qrcode lib
Home-page: https://github.com/phamxtien/streamlit_qrcode_scanner
Author: Pham Xuan Tien
Author-email: phamxtien@gmail.com
License: UNKNOWN
Platform: UNKNOWN
Requires-Python: >=3.9
License-File: LICENSE
